{
  "category": "clear",
  "count": 15,
  "products": [
    {
      "device_name": "OnePlus 13R",
      "device_brand": "OnePlus",
      "device_model": "13R",
      "device_variant": "",
      "url": "https://www.spigen.com/products/oneplus-13-series-ultra-hybrid",
      "product_brand": "Spigen",
      "product_model": "Ultra Hybrid",
      "title": "Spigen Ultra Hybrid MagFit Designed for OnePlus 13R Case - Crystal Clear",
      "price": "$24.99",
      "category": "cases-and-protection",
      "case_type": "clear",
      "protection_level": "clear",
      "clarity": "crystal clear",
      "materials": "TPU bumper + PC back",
      "features": [
        "Anti-yellowing",
        "MagSafe compatible",
        "Raised bezels",
        "Shock-absorbing",
        "Scratch resistant"
      ],
      "yellowing_resistance": "Yes"
    },
    {
      "device_name": "OnePlus 13R",
      "device_brand": "OnePlus",
      "device_model": "13R",
      "device_variant": "",
      "url": "https://www.ringkestore.com/products/oneplus-13r-case-fusion-x",
      "product_brand": "Ringke",
      "product_model": "Fusion",
      "title": "Ringke Fusion Compatible with OnePlus 13R Case - Crystal Clear",
      "price": "$16.99",
      "category": "cases-and-protection",
      "case_type": "clear",
      "protection_level": "clear",
      "clarity": "crystal clear",
      "materials": "TPU bumper + PC back",
      "features": [
        "Anti-yellowing",
        "Shockproof",
        "Raised bezels",
        "Scratch resistant"
      ],
      "yellowing_resistance": "Yes"
    },
    {
      "device_name": "OnePlus 13R",
      "device_brand": "OnePlus",
      "device_model": "13R",
      "device_variant": "",
      "url": "https://dbrand.com/shop/ghost/oneplus-13r-clear-cases",
      "product_brand": "dbrand",
      "product_model": "Ghost",
      "title": "dbrand Ghost Case for OnePlus 13R - Prism (Crystal Clear)",
      "price": "$49.99",
      "category": "cases-and-protection",
      "case_type": "clear",
      "protection_level": "clear",
      "clarity": "crystal clear",
      "materials": "Aramid fiber infused TPU",
      "features": [
        "Anti-yellowing",
        "Premium grip",
        "Scratch resistant",
        "Shock protection"
      ],
      "yellowing_resistance": "Yes"
    },
    {
      "device_name": "OnePlus 13R",
      "device_brand": "OnePlus",
      "device_model": "13R",
      "device_variant": "",
      "url": "https://www.esrtech.com",
      "product_brand": "ESR",
      "product_model": "Zero Yellowing",
      "title": "ESR for OnePlus 13R Case, Cyber Tough Crystal Clear with Yellowing Resistance",
      "price": "$19.99",
      "category": "cases-and-protection",
      "case_type": "clear",
      "protection_level": "clear",
      "clarity": "crystal clear",
      "materials": "TPU + PC hybrid",
      "features": [
        "Anti-yellowing",
        "Military-grade protection",
        "Raised bezels",
        "Scratch resistant"
      ],
      "yellowing_resistance": "Yes"
    },
    {
      "device_name": "OnePlus 13R",
      "device_brand": "OnePlus",
      "device_model": "13R",
      "device_variant": "",
      "url": "https://thecaseology.com/index.html",
      "product_brand": "Caseology",
      "product_model": "Skyfall",
      "title": "Caseology Skyfall for OnePlus 13R - Crystal Clear",
      "price": "$21.99",
      "category": "cases-and-protection",
      "case_type": "clear",
      "protection_level": "clear",
      "clarity": "crystal clear",
      "materials": "TPU sides + PC back",
      "features": [
        "Anti-yellowing",
        "Pocket-friendly",
        "Raised bezels",
        "Scratch resistant"
      ],
      "yellowing_resistance": "Yes"
    },
    {
      "device_name": "OnePlus 13R",
      "device_brand": "OnePlus",
      "device_model": "13R",
      "device_variant": "",
      "url": "https://www.spigen.com/products/oneplus-13-series-ultra-hybrid",
      "product_brand": "Spigen",
      "product_model": "Ultra Hybrid",
      "title": "Spigen Ultra Hybrid MagFit Designed for OnePlus 13R Case - Crystal Clear",
      "price": "$24.99",
      "category": "cases-and-protection",
      "case_type": "clear",
      "protection_level": "clear",
      "clarity": "crystal clear",
      "materials": "TPU bumper + PC back",
      "features": [
        "Anti-yellowing",
        "MagSafe compatible",
        "Raised bezels",
        "Shock-absorbing",
        "Scratch resistant"
      ],
      "yellowing_resistance": "Yes"
    },
    {
      "device_name": "OnePlus 13R",
      "device_brand": "OnePlus",
      "device_model": "13R",
      "device_variant": "",
      "url": "https://www.ringkestore.com/products/oneplus-13r-case-fusion-x",
      "product_brand": "Ringke",
      "product_model": "Fusion",
      "title": "Ringke Fusion Compatible with OnePlus 13R Case - Crystal Clear",
      "price": "$16.99",
      "category": "cases-and-protection",
      "case_type": "clear",
      "protection_level": "clear",
      "clarity": "crystal clear",
      "materials": "TPU bumper + PC back",
      "features": [
        "Anti-yellowing",
        "Shockproof",
        "Raised bezels",
        "Scratch resistant"
      ],
      "yellowing_resistance": "Yes"
    },
    {
      "device_name": "OnePlus 13R",
      "device_brand": "OnePlus",
      "device_model": "13R",
      "device_variant": "",
      "url": "https://dbrand.com/search?productTypes=ghost&brands=oneplus",
      "product_brand": "dbrand",
      "product_model": "Ghost Case 2.0",
      "title": "dbrand Ghost Case 2.0 for OnePlus 13R - Prism / Clear",
      "price": "$49.99",
      "category": "cases-and-protection",
      "case_type": "clear",
      "protection_level": "clear",
      "clarity": "crystal clear",
      "materials": "Microfiber-lined TPU",
      "features": [
        "Anti-yellowing",
        "Maximum clarity",
        "Scratch resistant",
        "Shock protection"
      ],
      "yellowing_resistance": "Yes"
    },
    {
      "device_name": "OnePlus 13R",
      "device_brand": "OnePlus",
      "device_model": "13R",
      "device_variant": "",
      "url": "https://www.esrtech.com",
      "product_brand": "ESR",
      "product_model": "Zero Yellowing",
      "title": "ESR for OnePlus 13R Case, Designed for MagSafe, Zero Yellowing Clear Case",
      "price": "$19.99",
      "category": "cases-and-protection",
      "case_type": "clear",
      "protection_level": "clear",
      "clarity": "crystal clear",
      "materials": "TPU + PC hybrid",
      "features": [
        "Zero yellowing",
        "MagSafe compatible",
        "Raised bezels",
        "Scratch resistant"
      ],
      "yellowing_resistance": "Yes"
    },
    {
      "device_name": "OnePlus 13R",
      "device_brand": "OnePlus",
      "device_model": "13R",
      "device_variant": "",
      "url": "https://thecaseology.com/index.html",
      "product_brand": "Caseology",
      "product_model": "Skyfall",
      "title": "Caseology Skyfall for OnePlus 13R, Clear Case with Anti-Yellowing Technology",
      "price": "$21.99",
      "category": "cases-and-protection",
      "case_type": "clear",
      "protection_level": "clear",
      "clarity": "crystal clear",
      "materials": "TPU sides + PC back",
      "features": [
        "Anti-yellowing",
        "Military grade drop protection",
        "Raised bezels",
        "Scratch resistant"
      ],
      "yellowing_resistance": "Yes"
    },
    {
      "device_name": "OnePlus 13R",
      "device_brand": "OnePlus",
      "device_model": "13R",
      "device_variant": "",
      "url": "https://www.spigen.com/products/oneplus-13-series-ultra-hybrid",
      "product_brand": "Spigen",
      "product_model": "Ultra Hybrid",
      "title": "Spigen Ultra Hybrid MagFit Designed for OnePlus 13R Case - Crystal Clear",
      "price": "$24.99",
      "category": "cases-and-protection",
      "case_type": "clear",
      "protection_level": "clear",
      "clarity": "crystal clear",
      "materials": "TPU bumper + PC back",
      "features": [
        "Anti-yellowing",
        "MagSafe compatible",
        "Raised bezels",
        "Shock-absorbing",
        "Scratch resistant"
      ],
      "yellowing_resistance": "Yes"
    },
    {
      "device_name": "OnePlus 13R",
      "device_brand": "OnePlus",
      "device_model": "13R",
      "device_variant": "",
      "url": "https://www.ringkestore.com/products/oneplus-13r-case-fusion-x",
      "product_brand": "Ringke",
      "product_model": "Fusion",
      "title": "Ringke Fusion Crystal Clear Designed for OnePlus 13R Case - Military Grade Protection",
      "price": "$16.99",
      "category": "cases-and-protection",
      "case_type": "clear",
      "protection_level": "clear",
      "clarity": "crystal clear",
      "materials": "TPU bumper + PC back",
      "features": [
        "Anti-yellowing",
        "Shockproof",
        "Raised bezels",
        "Scratch resistant"
      ],
      "yellowing_resistance": "Yes"
    },
    {
      "device_name": "OnePlus 13R",
      "device_brand": "OnePlus",
      "device_model": "13R",
      "device_variant": "",
      "url": "https://dbrand.com/search?productTypes=ghost&brands=oneplus",
      "product_brand": "dbrand",
      "product_model": "Ghost Case 2.0",
      "title": "dbrand Ghost Case 2.0 for OnePlus 13R - Precision-Grip Transparent Case",
      "price": "$49.99",
      "category": "cases-and-protection",
      "case_type": "clear",
      "protection_level": "clear",
      "clarity": "crystal clear",
      "materials": "Microfiber-lined TPU",
      "features": [
        "Anti-yellowing",
        "Scratch resistant",
        "Shock-absorbing",
        "Raised bezels"
      ],
      "yellowing_resistance": "Yes"
    },
    {
      "device_name": "OnePlus 13R",
      "device_brand": "OnePlus",
      "device_model": "13R",
      "device_variant": "",
      "url": "https://www.esrtech.com",
      "product_brand": "ESR",
      "product_model": "Zero Yellowing",
      "title": "ESR for OnePlus 13R Case Crystal Clear with Yellowing Resistance - Military Grade Protection",
      "price": "$17.99",
      "category": "cases-and-protection",
      "case_type": "clear",
      "protection_level": "clear",
      "clarity": "crystal clear",
      "materials": "TPU + PC hybrid",
      "features": [
        "Anti-yellowing",
        "Shockproof",
        "Raised bezels",
        "Scratch resistant"
      ],
      "yellowing_resistance": "Yes"
    },
    {
      "device_name": "OnePlus 13R",
      "device_brand": "OnePlus",
      "device_model": "13R",
      "device_variant": "",
      "url": "https://thecaseology.com/index.html",
      "product_brand": "Caseology",
      "product_model": "Skyfall",
      "title": "Caseology Skyfall for OnePlus 13R - Crystal Clear Transparent Case with Anti-Yellowing Tech",
      "price": "$19.99",
      "category": "cases-and-protection",
      "case_type": "clear",
      "protection_level": "clear",
      "clarity": "crystal clear",
      "materials": "TPU sides + PC back",
      "features": [
        "Anti-yellowing",
        "Shock-absorbing",
        "Raised bezels",
        "Scratch resistant"
      ],
      "yellowing_resistance": "Yes"
    }
  ],
  "saved_at": "2025-12-30T19:48:19Z",
  "case_type": "clear"
}